guyamoe_api_types/__init__.py
guyamoe_api_types/all_groups.py
guyamoe_api_types/all_series.py
guyamoe_api_types/py.typed
guyamoe_api_types/search_index.py
guyamoe_api_types/series.py
guyamoe_api_types/series_groups.py
guyamoe_api_types/series_page_data.py
guyamoe_api_types/series_volume_cover.py
guyamoe_api_types/series_volume_covers.py
guyamoe_api_types-1.0.dist-info/METADATA
guyamoe_api_types-1.0.dist-info/WHEEL
guyamoe_api_types-1.0.dist-info/top_level.txt
guyamoe_api_types-1.0.dist-info/RECORD
