Metadata-Version: 2.1
Name: guyamoe-api-types
Version: 1.0
Summary: Types for the api at guya.moe
Home-page: https://github.com/TypedAPIs/guyamoe
Author: PythonCoderAS
Author-email: sarkaraoyan@gmail.com
Project-URL: Bug Tracker, https://github.com/TypedAPIs/guyamoe/issues
Classifier: Programming Language :: Python :: 3
Classifier: License :: OSI Approved :: MIT License
Classifier: Operating System :: OS Independent
Requires-Python: >=3.6
Requires-Dist: typing-extensions
